pyday/__init__.py
pyday/change_encode.py
pyday/change_lang.py
pyday/main.py
pyday/utils/fileIO.py
pyday-0.1.3.dist-info/LICENSE
pyday-0.1.3.dist-info/METADATA
pyday-0.1.3.dist-info/WHEEL
pyday-0.1.3.dist-info/entry_points.txt
pyday-0.1.3.dist-info/RECORD
