Metadata-Version: 2.1
Name: pyday
Version: 0.1.3
Summary: 
Author: AnsonCar
Author-email: anson1tsang@gmail.com
Requires-Python: >=3.10,<4.0
Classifier: Programming Language :: Python :: 3
Classifier: Programming Language :: Python :: 3.10
Classifier: Programming Language :: Python :: 3.11
Classifier: Programming Language :: Python :: 3.12
Classifier: Programming Language :: Python :: 3.13
Requires-Dist: opencc (>=1.1.9,<2.0.0)
Requires-Dist: typer (>=0.12.5,<0.13.0)
